nerforpdf/__init__.py
nerforpdf/highlight_pdf.py
nerforpdf/ner.py
nerforpdf/ner_api.py
nerforpdf/text_preprocessing.py
nerforpdf-0.0.4.dist-info/METADATA
nerforpdf-0.0.4.dist-info/WHEEL
nerforpdf-0.0.4.dist-info/RECORD
