Metadata-Version: 2.1
Name: nerforpdf
Version: 0.0.4
Summary: Ce package highlight les entités dans un pdf
Project-URL: Homepage, https://github.com/ach2ashes/Internship_nlp
Author-email: Achraf Sbai <achraf.sbai2012@gmail.com>
Classifier: License :: OSI Approved :: MIT License
Classifier: Operating System :: OS Independent
Classifier: Programming Language :: Python :: 3
Requires-Python: >=3.7
